aws_tee/__init__.py
aws_tee/aws_tee.conf.example
aws_tee/cli.py
aws_tee-0.1.0.dist-info/licenses/LICENSE
aws_tee-0.1.0.dist-info/METADATA
aws_tee-0.1.0.dist-info/WHEEL
aws_tee-0.1.0.dist-info/entry_points.txt
aws_tee-0.1.0.dist-info/top_level.txt
aws_tee-0.1.0.dist-info/RECORD
