Metadata-Version: 2.4
Name: aws-tee
Version: 0.1.0
Summary: 標準入力をそのまま標準出力に流しつつ、同じ内容を CloudWatch Logs と S3 に送る tee 風コマンド
Author-email: n_h <h.10x64@gmail.com>
License-Expression: CC0-1.0
Project-URL: Homepage, https://github.com/h10x64/AWS-tee
Project-URL: Documentation, https://github.com/h10x64/AWS-tee#readme
Project-URL: Repository, https://github.com/h10x64/AWS-tee
Project-URL: Issues, https://github.com/h10x64/AWS-tee/issues
Project-URL: Bug Tracker, https://github.com/h10x64/AWS-tee/issues
Keywords: aws,cloudwatch,s3,tee,logging
Classifier: Development Status :: 4 - Beta
Classifier: Intended Audience :: Developers
Classifier: Programming Language :: Python :: 3
Classifier: Programming Language :: Python :: 3.7
Classifier: Programming Language :: Python :: 3.8
Classifier: Programming Language :: Python :: 3.9
Classifier: Programming Language :: Python :: 3.10
Classifier: Programming Language :: Python :: 3.11
Classifier: Programming Language :: Python :: 3.12
Classifier: Programming Language :: Python :: 3.13
Classifier: Topic :: System :: Logging
Classifier: Topic :: Utilities
Requires-Python: >=3.7
License-File: LICENSE
Requires-Dist: cloudwatchlogs-s3-stream-descriptor
Provides-Extra: dev
Requires-Dist: pytest>=7.0.0; extra == "dev"
Dynamic: license-file
